qdataclass/__init__.py
qdataclass/__init__.pyi
qdataclass/py.typed
qdataclass/qdataclass.py
qdataclass/qdataclass.pyi
qdataclass-1.0.3.dist-info/LICENSE
qdataclass-1.0.3.dist-info/METADATA
qdataclass-1.0.3.dist-info/WHEEL
qdataclass-1.0.3.dist-info/top_level.txt
qdataclass-1.0.3.dist-info/RECORD
