Metadata-Version: 2.1
Name: qdataclass
Version: 1.0.3
Summary: 自动生成QProperty的getter setter notify
Home-page: UNKNOWN
Author: 林柏君
Author-email: 1355767057@qq.com
License: UNKNOWN
Platform: UNKNOWN
License-File: LICENSE
